{
  "data": [
      {
      "id": 1,
      "title": "Old Memory",
      "artist": "三輪学",
      "pic": "http://aufree.qiniudn.com/images/album/img20/89520/4280541424067346.jpg",
      "music_url" : "http://aufree.qiniudn.com/1770059653_2050944_l.mp3",
      "file_name" : "1770059653_2050944_l",
      "content": "此曲旋律轻快, 美妙, 仿佛欲将人带入一个十分干净且祥和的小镇... "
      },
      {
      "id": 2,
      "title": "A Little Story",
      "artist": "Valentin",
      "pic": "https://gimg2.baidu.com/image_search/src=http%3A%2F%2Fhbimg.b0.upaiyun.com%2F062562fabd8a6d464959979bb07244f60bd947ad116f4-PtNoi6_fw658&refer=http%3A%2F%2Fhbimg.b0.upaiyun.com&app=2002&size=f9999,10000&q=a80&n=0&g=0n&fmt=auto?sec=1653211190&t=6b1fe99c49ac4e7c9c4374eb1f93f8b9",
      "music_url" : "http://aufree.qiniudn.com/1770040300_2031329_l.mp3",
      "file_name" : "1770040300_2031329_l",
      "content": "整首歌曲曲调轻松欢快, 这几天一直循环播放~"
      },
      {
      "id": 3,
      "title": "letter song",
      "artist": "ヲタみん",
      "pic": "https://bkimg.cdn.bcebos.com/pic/a8ec8a13632762d064d106f9a2ec08fa503dc68d?x-bce-process=image/watermark,image_d2F0ZXIvYmFpa2U4MA==,g_7,xp_5,yp_5/format,f_auto",
      "music_url" : "http://aufree.qiniudn.com/1771694697_4194836_l.mp3",
      "file_name" : "1771694697_4194836_l",
      "content": "致十年后的自己，人生能有几个十年"
      },
      {
      "id": 4,
      "title": "DIY",
      "artist": "MAC ZHOU",
      "pic": "https://gimg2.baidu.com/image_search/src=http%3A%2F%2Fup.enterdesk.com%2Fedpic_source%2F95%2Fe2%2F09%2F95e20960f6bcb6d444dfa59d142e9300.jpg&refer=http%3A%2F%2Fup.enterdesk.com&app=2002&size=f9999,10000&q=a80&n=0&g=0n&fmt=auto?sec=1653210977&t=878bdbbb002cafb9480277e58ea6bf58",
      "music_url" : "http://music.163.com/song/media/outer/url?id=554191055.mp3",
      "file_name" : "1771694697",
      "content": "致十年后的自己，人生能有几个十年"
      }
  ]
}

